Metadata-Version: 1.0
Name: great-udacity-distributions
Version: 0.2
Summary: Gaussian and Binomial distributions
Home-page: UNKNOWN
Author: Great Thavapatikom
Author-email: UNKNOWN
License: UNKNOWN
Platform: UNKNOWN
